Metadata-Version: 2.1
Name: 20CS30064MyPackage
Version: 0.0.1
Summary: A package
Home-page: https://github.com/
Author: Anamitra Mukhopadhyay
Author-email: anamitra137@gmail.com
License: UNKNOWN
Platform: UNKNOWN
Classifier: Programming Language :: Python :: 3
Classifier: License :: OSI Approved :: MIT License
Classifier: Operating System :: OS Independent
Requires-Python: >=3.6
License-File: LICENSE
